kBmc/__init__.py
kbmc-3.0.43.dist-info/LICENSE
kbmc-3.0.43.dist-info/METADATA
kbmc-3.0.43.dist-info/WHEEL
kbmc-3.0.43.dist-info/top_level.txt
kbmc-3.0.43.dist-info/RECORD
