Metadata-Version: 2.1
Name: kbmc
Version: 3.0.43
Summary: Kage's Intelgent BMC handler
Home-page: https://github.com/kagepark/kBmc
Author: Kage Park
License: MIT
Platform: UNKNOWN
Classifier: Programming Language :: Python :: 2
Classifier: Programming Language :: Python :: 3
Classifier: License :: OSI Approved :: MIT License
Classifier: Operating System :: OS Independent
License-File: LICENSE
